src/alu.sv
module alu (
    input  [31:0] a,      
    input  [31:0] b,       
    input  [4:0]  alu_op,  // Operación ALU: 
    output [31:0] alu_res  
);

    localparam ADD  = 5'b00000; // Suma
    localparam SUB  = 5'b00001; // Resta
    localparam SLL  = 5'b00010; // Shift lógico a la izquierda
    localparam SLT  = 5'b00011; // Set menor que (signed)
    localparam SLTU = 5'b00100; // Set menor que (unsigned)
    localparam XOR_ = 5'b00101; // XOR
    localparam SRL  = 5'b00110; // Shift lógico a la derecha
    localparam SRA  = 5'b00111; // Shift aritmético a la derecha
    localparam OR_  = 5'b01000; // OR
    localparam AND_ = 5'b01001; // AND

	 wire signed [31:0] a_signed = a;
	 wire signed [31:0] b_signed = b;
	 wire [31:0] a_unsigned= a;
	 wire [31:0] b_unsigned = b;
	 
    reg [31:0] result;

    always @(*) begin
        case (alu_op)
            ADD:   result = a + b;
            SUB:   result = a - b;
            SLL:   result = a << b[4:0];               // Se usan 5 bits para shift
            SLT:   result = {31'b0, a_signed < b_signed};
            SLTU:  result = {31'b0, a_unsigned < b_unsigned};
            XOR_:  result = a ^ b;
            SRL:   result = a >> b[4:0];               // Shift lógico
            SRA:   result = a_signed >>> b[4:0];     // Shift aritmético
            OR_:   result = a | b;
            AND_:  result = a & b;
            default: result = 32'b0;                   // Caso por defecto
        endcase
    end

    assign alu_res = result;

endmodule

test/alu/alu_tb.sv
`timescale 1ns/1ps
module tb_alu;
  logic [31:0] a, b;
  logic [4:0] alu_op;
  wire [31:0] alu_res;

  localparam ADD  = 5'b00000;
  localparam SUB  = 5'b00001;
  localparam SLL  = 5'b00010;
  localparam SLT  = 5'b00011;
  localparam SLTU = 5'b00100;
  localparam XOR_ = 5'b00101;
  localparam SRL  = 5'b00110;
  localparam SRA  = 5'b00111;
  localparam OR_  = 5'b01000;
  localparam AND_ = 5'b01001;

  alu dut(.a(a), .b(b), .alu_op(alu_op), .alu_res(alu_res));

  initial begin
    $dumpfile("test/alu/alu_tb.vcd");
    $dumpvars(0, tb_alu);

    a = 32'h0000000A; b = 32'h00000003; alu_op = ADD;  #10; $display("ADD a=%h b=%h res=%h", a, b, alu_res);
    a = 32'h0000000A; b = 32'h00000003; alu_op = SUB;  #10; $display("SUB a=%h b=%h res=%h", a, b, alu_res);
    a = 32'h00000001; b = 32'h00000003; alu_op = SLL;  #10; $display("SLL a=%h b=%h res=%h", a, b, alu_res);
    a = 32'h00000010; b = 32'h00000003; alu_op = SRL;  #10; $display("SRL a=%h b=%h res=%h", a, b, alu_res);
    a = 32'h80000000; b = 32'h0000001F; alu_op = SRA;  #10; $display("SRA a=%h b=%h res=%h", a, b, alu_res);
    a = 32'h0000000F; b = 32'h000000F0; alu_op = XOR_; #10; $display("XOR a=%h b=%h res=%h", a, b, alu_res);
    a = 32'h0000000F; b = 32'h000000F0; alu_op = OR_;  #10; $display("OR  a=%h b=%h res=%h", a, b, alu_res);
    a = 32'h0000000F; b = 32'h000000F0; alu_op = AND_; #10; $display("AND a=%h b=%h res=%h", a, b, alu_res);
    a = 32'hFFFF_FFFF; b = 32'h0000_0001; alu_op = SLT;  #10; $display("SLT a=%h b=%h res=%h", a, b, alu_res);
    a = 32'h0000_0001; b = 32'hFFFF_FFFF; alu_op = SLTU; #10; $display("SLTU a=%h b=%h res=%h", a, b, alu_res);

    #10 $finish;
  end
endmodule

test/alu/alu_tb.vcd
$date
	Tue Nov 25 16:09:14 2025
$end
$version
	Icarus Verilog
$end
$timescale
	1ps
$end
$scope module tb_alu $end
$var wire 32 ! alu_res [31:0] $end
$var parameter 5 " ADD $end
$var parameter 5 # AND_ $end
$var parameter 5 $ OR_ $end
$var parameter 5 % SLL $end
$var parameter 5 & SLT $end
$var parameter 5 ' SLTU $end
$var parameter 5 ( SRA $end
$var parameter 5 ) SRL $end
$var parameter 5 * SUB $end
$var parameter 5 + XOR_ $end
$var reg 32 , a [31:0] $end
$var reg 5 - alu_op [4:0] $end
$var reg 32 . b [31:0] $end
$scope module dut $end
$var wire 32 / a [31:0] $end
$var wire 32 0 a_signed [31:0] $end
$var wire 32 1 a_unsigned [31:0] $end
$var wire 5 2 alu_op [4:0] $end
$var wire 32 3 alu_res [31:0] $end
$var wire 32 4 b [31:0] $end
$var wire 32 5 b_signed [31:0] $end
$var wire 32 6 b_unsigned [31:0] $end
$var parameter 5 7 ADD $end
$var parameter 5 8 AND_ $end
$var parameter 5 9 OR_ $end
$var parameter 5 : SLL $end
$var parameter 5 ; SLT $end
$var parameter 5 < SLTU $end
$var parameter 5 = SRA $end
$var parameter 5 > SRL $end
$var parameter 5 ? SUB $end
$var parameter 5 @ XOR_ $end
$var reg 32 A result [31:0] $end
$upscope $end
$upscope $end
$enddefinitions $end
$comment Show the parameter values. $end
$dumpall
b101 @
b1 ?
b110 >
b111 =
b100 <
b11 ;
b10 :
b1000 9
b1001 8
b0 7
b101 +
b1 *
b110 )
b111 (
b100 '
b11 &
b10 %
b1000 $
b1001 #
b0 "
$end
#0
$dumpvars
b1101 A
b11 6
b11 5
b11 4
b1101 3
b0 2
b1010 1
b1010 0
b1010 /
b11 .
b0 -
b1010 ,
b1101 !
$end
#10000
b111 !
b111 3
b111 A
b1 -
b1 2
#20000
b1000 !
b1000 3
b1000 A
b10 -
b10 2
b1 0
b1 1
b1 ,
b1 /
#30000
b10 !
b10 3
b10 A
b110 -
b110 2
b10000 0
b10000 1
b10000 ,
b10000 /
#40000
b11111111111111111111111111111111 !
b11111111111111111111111111111111 3
b11111111111111111111111111111111 A
b111 -
b111 2
b11111 5
b11111 6
b11111 .
b11111 4
b10000000000000000000000000000000 0
b10000000000000000000000000000000 1
b10000000000000000000000000000000 ,
b10000000000000000000000000000000 /
#50000
b11111111 !
b11111111 3
b11111111 A
b101 -
b101 2
b11110000 5
b11110000 6
b11110000 .
b11110000 4
b1111 0
b1111 1
b1111 ,
b1111 /
#60000
b1000 -
b1000 2
#70000
b0 !
b0 3
b0 A
b1001 -
b1001 2
#80000
b1 !
b1 3
b1 A
b11 -
b11 2
b1 5
b1 6
b1 .
b1 4
b11111111111111111111111111111111 0
b11111111111111111111111111111111 1
b11111111111111111111111111111111 ,
b11111111111111111111111111111111 /
#90000
b100 -
b100 2
b11111111111111111111111111111111 5
b11111111111111111111111111111111 6
b11111111111111111111111111111111 .
b11111111111111111111111111111111 4
b1 0
b1 1
b1 ,
b1 /
